{
    "tournament": {
        "date": "2019-09-22",
        "name": "Lotus League #2 SMM Trial",
        "url": "https://mtgtop8.com/event?e=23226",
        "format": "Legacy",
        "players": 17
    },
    "decks": [
        {
            "date": "2019-09-22",
            "player": "Reto Sormani",
            "result": 1,
            "anchor_uri": "https://mtgtop8.com/event?e=23226&d=359706&f=LE",
            "mainboard": [
                {
                    "count": 3,
                    "name": "Snapcaster Mage"
                },
                {
                    "count": 3,
                    "name": "Monastery Mentor"
                },
                {
                    "count": 3,
                    "name": "Arcum's Astrolabe"
                },
                {
                    "count": 4,
                    "name": "Brainstorm"
                },
                {
                    "count": 4,
                    "name": "Swords to Plowshares"
                },
                {
                    "count": 2,
                    "name": "Spell Pierce"
                },
                {
                    "count": 2,
                    "name": "Force of Negation"
                },
                {
                    "count": 4,
                    "name": "Force of Will"
                },
                {
                    "count": 2,
                    "name": "Magmatic Sinkhole"
                },
                {
                    "count": 4,
                    "name": "Ponder"
                },
                {
                    "count": 2,
                    "name": "Council's Judgment"
                },
                {
                    "count": 1,
                    "name": "Back to Basics"
                },
                {
                    "count": 2,
                    "name": "Narset, Parter of Veils"
                },
                {
                    "count": 2,
                    "name": "Teferi, Time Raveler"
                },
                {
                    "count": 2,
                    "name": "Jace, the Mind Sculptor"
                },
                {
                    "count": 4,
                    "name": "Flooded Strand"
                },
                {
                    "count": 4,
                    "name": "Prismatic Vista"
                },
                {
                    "count": 5,
                    "name": "Snow-Covered Island"
                },
                {
                    "count": 2,
                    "name": "Scalding Tarn"
                },
                {
                    "count": 2,
                    "name": "Snow-Covered Plains"
                },
                {
                    "count": 1,
                    "name": "Snow-Covered Mountain"
                },
                {
                    "count": 1,
                    "name": "Tundra"
                },
                {
                    "count": 1,
                    "name": "Volcanic Island"
                }
            ],
            "sideboard": [
                {
                    "count": 1,
                    "name": "Back to Basics"
                },
                {
                    "count": 2,
                    "name": "Hydroblast"
                },
                {
                    "count": 2,
                    "name": "Pyroblast"
                },
                {
                    "count": 1,
                    "name": "Abrade"
                },
                {
                    "count": 1,
                    "name": "Celestial Purge"
                },
                {
                    "count": 2,
                    "name": "Rest in Peace"
                },
                {
                    "count": 1,
                    "name": "Palace Jailer"
                },
                {
                    "count": 2,
                    "name": "Supreme Verdict"
                },
                {
                    "count": 1,
                    "name": "Wear/Tear"
                },
                {
                    "count": 1,
                    "name": "Surgical Extraction"
                },
                {
                    "count": 1,
                    "name": "Gideon, Ally of Zendikar"
                }
            ],
            "notes": "This deck focuses on controlling the game by countering opponent's spells, removing threats with removal spells, and generating card advantage through cantrips like Brainstorm and Ponder. It also utilizes planeswalkers like Narset, Teferi, and Jace to further disrupt the opponent's game plan. The inclusion of Monastery Mentor provides a win condition that can quickly close out the game. The deck's mana base includes a mix of fetch lands and dual lands to ensure consistent access to all necessary colors of mana."
        },
        {
            "date": "2019-09-22",
            "player": "Samuele Frisina",
            "result": 2,
            "anchor_uri": "https://mtgtop8.com/event?e=23226&d=359707&f=LE",
            "mainboard": [
                {
                    "count": 1,
                    "name": "Verdant Catacombs"
                },
                {
                    "count": 3,
                    "name": "Underground Sea"
                },
                {
                    "count": 1,
                    "name": "Tundra"
                },
                {
                    "count": 1,
                    "name": "Tropical Island"
                },
                {
                    "count": 2,
                    "name": "Swamp"
                },
                {
                    "count": 1,
                    "name": "Scrubland"
                },
                {
                    "count": 4,
                    "name": "Polluted Delta"
                },
                {
                    "count": 3,
                    "name": "Misty Rainforest"
                },
                {
                    "count": 1,
                    "name": "Marsh Flats"
                },
                {
                    "count": 1,
                    "name": "Island"
                },
                {
                    "count": 2,
                    "name": "Forest"
                },
                {
                    "count": 1,
                    "name": "Bayou"
                },
                {
                    "count": 1,
                    "name": "Pernicious Deed"
                },
                {
                    "count": 2,
                    "name": "Noble Hierarch"
                },
                {
                    "count": 4,
                    "name": "Veteran Explorer"
                },
                {
                    "count": 4,
                    "name": "Baleful Strix"
                },
                {
                    "count": 1,
                    "name": "Phantasmal Image"
                },
                {
                    "count": 1,
                    "name": "Scavenging Ooze"
                },
                {
                    "count": 1,
                    "name": "Eternal Witness"
                },
                {
                    "count": 1,
                    "name": "Knight of Autumn"
                },
                {
                    "count": 1,
                    "name": "Leovold, Emissary of Trest"
                },
                {
                    "count": 1,
                    "name": "Plague Engineer"
                },
                {
                    "count": 1,
                    "name": "Plaguecrafter"
                },
                {
                    "count": 1,
                    "name": "Renegade Rallier"
                },
                {
                    "count": 1,
                    "name": "Glen Elendra Archmage"
                },
                {
                    "count": 1,
                    "name": "Hostage Taker"
                },
                {
                    "count": 1,
                    "name": "Meren of Clan Nel Toth"
                },
                {
                    "count": 1,
                    "name": "Siege Rhino"
                },
                {
                    "count": 1,
                    "name": "Custodi Lich"
                },
                {
                    "count": 1,
                    "name": "Thragtusk"
                },
                {
                    "count": 3,
                    "name": "Birthing Pod"
                },
                {
                    "count": 3,
                    "name": "Brainstorm"
                },
                {
                    "count": 3,
                    "name": "Abrupt Decay"
                },
                {
                    "count": 4,
                    "name": "Cabal Therapy"
                },
                {
                    "count": 1,
                    "name": "Sylvan Library"
                }
            ],
            "sideboard": [
                {
                    "count": 1,
                    "name": "Jace, the Mind Sculptor"
                },
                {
                    "count": 1,
                    "name": "Garruk Relentless"
                },
                {
                    "count": 1,
                    "name": "Toxic Deluge"
                },
                {
                    "count": 1,
                    "name": "Liliana, the Last Hope"
                },
                {
                    "count": 1,
                    "name": "Assassin's Trophy"
                },
                {
                    "count": 2,
                    "name": "Veil of Summer"
                },
                {
                    "count": 2,
                    "name": "Surgical Extraction"
                },
                {
                    "count": 2,
                    "name": "Duress"
                },
                {
                    "count": 1,
                    "name": "Nezahal, Primal Tide"
                },
                {
                    "count": 1,
                    "name": "Orzhov Pontiff"
                },
                {
                    "count": 1,
                    "name": "Meddling Mage"
                },
                {
                    "count": 1,
                    "name": "Ethersworn Canonist"
                }
            ],
            "notes": "The deck focuses on utilizing the Nic Fit archetype to control the game by playing threats and disrupting the opponent's game plan. It uses Veteran Explorer to ramp up and fix mana, while cards like Baleful Strix and Plague Engineer provide value through card advantage and creature removal. The deck also includes versatile cards like Birthing Pod and Hostage Taker to adapt to different situations, while powerful creatures like Leovold, Emissary of Trest and Siege Rhino help close out the game. Overall, the deck aims to outvalue and outlast the opponent through proactive control strategies."
        },
        {
            "date": "2019-09-22",
            "player": "Christian Vittoni",
            "result": 3,
            "anchor_uri": "https://mtgtop8.com/event?e=23226&d=359709&f=LE",
            "mainboard": [
                {
                    "count": 4,
                    "name": "Elvish Reclaimer"
                },
                {
                    "count": 4,
                    "name": "Vampire Hexmage"
                },
                {
                    "count": 2,
                    "name": "Dark Confidant"
                },
                {
                    "count": 2,
                    "name": "Sylvan Safekeeper"
                },
                {
                    "count": 4,
                    "name": "Mox Diamond"
                },
                {
                    "count": 4,
                    "name": "Crop Rotation"
                },
                {
                    "count": 3,
                    "name": "Abrupt Decay"
                },
                {
                    "count": 1,
                    "name": "Assassin's Trophy"
                },
                {
                    "count": 4,
                    "name": "Duress"
                },
                {
                    "count": 3,
                    "name": "Thoughtseize"
                },
                {
                    "count": 1,
                    "name": "Sylvan Scrying"
                },
                {
                    "count": 1,
                    "name": "Sylvan Library"
                },
                {
                    "count": 4,
                    "name": "Verdant Catacombs"
                },
                {
                    "count": 4,
                    "name": "Dark Depths"
                },
                {
                    "count": 4,
                    "name": "Thespian's Stage"
                },
                {
                    "count": 4,
                    "name": "Urborg, Tomb of Yawgmoth"
                },
                {
                    "count": 2,
                    "name": "Bayou"
                },
                {
                    "count": 2,
                    "name": "Nurturing Peatland"
                },
                {
                    "count": 1,
                    "name": "Sejiri Steppe"
                },
                {
                    "count": 2,
                    "name": "Wasteland"
                },
                {
                    "count": 1,
                    "name": "Forest"
                },
                {
                    "count": 1,
                    "name": "Swamp"
                },
                {
                    "count": 1,
                    "name": "Bojuka Bog"
                },
                {
                    "count": 1,
                    "name": "Karakas"
                }
            ],
            "sideboard": [
                {
                    "count": 1,
                    "name": "Assassin's Trophy"
                },
                {
                    "count": 2,
                    "name": "Hymn to Tourach"
                },
                {
                    "count": 3,
                    "name": "Pithing Needle"
                },
                {
                    "count": 2,
                    "name": "Plague Engineer"
                },
                {
                    "count": 2,
                    "name": "Force of Vigor"
                },
                {
                    "count": 2,
                    "name": "Surgical Extraction"
                },
                {
                    "count": 2,
                    "name": "Choke"
                },
                {
                    "count": 1,
                    "name": "Veil of Summer"
                }
            ],
            "notes": "The main concept of this deck is to quickly assemble the Dark Depths and Thespian's Stage combo to create a 20/20 flying indestructible creature. The deck focuses on searching for and protecting the combo pieces, while disrupting opponents with discard spells like Duress and Thoughtseize. The deck also includes removal spells like Abrupt Decay and Assassin's Trophy for dealing with threats. The mana base is carefully crafted to support the combo and provide flexibility with cards like Urborg, Tomb of Yawgmoth and Karakas. Overall, the deck aims to win through a powerful and difficult to interact with combo."
        },
        {
            "date": "2019-09-22",
            "player": "Lorenzo Marinuzzi",
            "result": 3,
            "anchor_uri": "https://mtgtop8.com/event?e=23226&d=359708&f=LE",
            "mainboard": [
                {
                    "count": 4,
                    "name": "Simian Spirit Guide"
                },
                {
                    "count": 1,
                    "name": "Hazoret the Fervent"
                },
                {
                    "count": 4,
                    "name": "Legion Warboss"
                },
                {
                    "count": 4,
                    "name": "Goblin Rabblemaster"
                },
                {
                    "count": 2,
                    "name": "Magus of the Moon"
                },
                {
                    "count": 4,
                    "name": "Chrome Mox"
                },
                {
                    "count": 4,
                    "name": "Chalice of the Void"
                },
                {
                    "count": 4,
                    "name": "Trinisphere"
                },
                {
                    "count": 3,
                    "name": "Fiery Confluence"
                },
                {
                    "count": 4,
                    "name": "Blood Moon"
                },
                {
                    "count": 4,
                    "name": "Karn, the Great Creator"
                },
                {
                    "count": 4,
                    "name": "Chandra, Torch of Defiance"
                },
                {
                    "count": 4,
                    "name": "City of Traitors"
                },
                {
                    "count": 11,
                    "name": "Mountain"
                },
                {
                    "count": 4,
                    "name": "Ancient Tomb"
                }
            ],
            "sideboard": [
                {
                    "count": 1,
                    "name": "Winter Orb"
                },
                {
                    "count": 1,
                    "name": "Liquimetal Coating"
                },
                {
                    "count": 1,
                    "name": "Sorcerous Spyglass"
                },
                {
                    "count": 3,
                    "name": "Ensnaring Bridge"
                },
                {
                    "count": 3,
                    "name": "Scab-Clan Berserker"
                },
                {
                    "count": 4,
                    "name": "Leyline of the Void"
                },
                {
                    "count": 1,
                    "name": "Helm of Obedience"
                },
                {
                    "count": 1,
                    "name": "Mycosynth Lattice"
                }
            ],
            "notes": "The deck focuses on locking down the opponent's mana base with cards like Blood Moon, Magus of the Moon, and Chalice of the Void while quickly pressuring them with aggressive creatures like Legion Warboss, Goblin Rabblemaster, and Hazoret the Fervent. The deck also utilizes powerful planeswalkers like Karn, the Great Creator and Chandra, Torch of Defiance to further disrupt the opponent's game plan and provide additional threats. With a combination of mana denial and aggressive creatures, this deck aims to overwhelm the opponent before they can establish their own game plan."
        },
        {
            "date": "2019-09-22",
            "player": "Tino Martino",
            "result": 5,
            "anchor_uri": "https://mtgtop8.com/event?e=23226&d=359712&f=LE",
            "mainboard": [
                {
                    "count": 4,
                    "name": "Death's Shadow"
                },
                {
                    "count": 4,
                    "name": "Delver of Secrets"
                },
                {
                    "count": 2,
                    "name": "Gurmag Angler"
                },
                {
                    "count": 4,
                    "name": "Street Wraith"
                },
                {
                    "count": 2,
                    "name": "Berserk"
                },
                {
                    "count": 4,
                    "name": "Brainstorm"
                },
                {
                    "count": 4,
                    "name": "Daze"
                },
                {
                    "count": 2,
                    "name": "Dismember"
                },
                {
                    "count": 2,
                    "name": "Fatal Push"
                },
                {
                    "count": 4,
                    "name": "Force of Will"
                },
                {
                    "count": 1,
                    "name": "Diabolic Edict"
                },
                {
                    "count": 1,
                    "name": "Stubborn Denial"
                },
                {
                    "count": 4,
                    "name": "Ponder"
                },
                {
                    "count": 1,
                    "name": "Reanimate"
                },
                {
                    "count": 4,
                    "name": "Thoughtseize"
                },
                {
                    "count": 2,
                    "name": "Misty Rainforest"
                },
                {
                    "count": 2,
                    "name": "Overgrown Tomb"
                },
                {
                    "count": 4,
                    "name": "Polluted Delta"
                },
                {
                    "count": 1,
                    "name": "Tropical Island"
                },
                {
                    "count": 1,
                    "name": "Underground Sea"
                },
                {
                    "count": 2,
                    "name": "Verdant Catacombs"
                },
                {
                    "count": 4,
                    "name": "Wasteland"
                },
                {
                    "count": 2,
                    "name": "Watery Grave"
                }
            ],
            "sideboard": [
                {
                    "count": 1,
                    "name": "Damping Sphere"
                },
                {
                    "count": 1,
                    "name": "Winter Orb"
                },
                {
                    "count": 1,
                    "name": "Leovold, Emissary of Trest"
                },
                {
                    "count": 2,
                    "name": "Dread of Night"
                },
                {
                    "count": 1,
                    "name": "Sylvan Library"
                },
                {
                    "count": 2,
                    "name": "Abrupt Decay"
                },
                {
                    "count": 2,
                    "name": "Hydroblast"
                },
                {
                    "count": 3,
                    "name": "Surgical Extraction"
                },
                {
                    "count": 1,
                    "name": "Vapor Snag"
                },
                {
                    "count": 1,
                    "name": "Liliana, the Last Hope"
                }
            ],
            "notes": "The main concept of this Aggro - Death's Shadow deck is to use cards like Death's Shadow, Delver of Secrets, and Gurmag Angler to quickly apply pressure on the opponent while also disrupting their game plan with cards like Thoughtseize, Daze, and Force of Will. The deck also uses cards like Berserk and Stubborn Denial to close out games quickly and protect its threats. The mana base is built to support a fast and consistent game plan, with access to various colors for spells like Brainstorm and Fatal Push."
        },
        {
            "date": "2019-09-22",
            "player": "Guidicelli Nicola",
            "result": 5,
            "anchor_uri": "https://mtgtop8.com/event?e=23226&d=359713&f=LE",
            "mainboard": [
                {
                    "count": 4,
                    "name": "Dreadhorde Arcanist"
                },
                {
                    "count": 3,
                    "name": "Snapcaster Mage"
                },
                {
                    "count": 2,
                    "name": "True-Name Nemesis"
                },
                {
                    "count": 4,
                    "name": "Brainstorm"
                },
                {
                    "count": 2,
                    "name": "Fatal Push"
                },
                {
                    "count": 3,
                    "name": "Lightning Bolt"
                },
                {
                    "count": 1,
                    "name": "Liliana's Triumph"
                },
                {
                    "count": 1,
                    "name": "Force of Negation"
                },
                {
                    "count": 3,
                    "name": "Kolaghan's Command"
                },
                {
                    "count": 4,
                    "name": "Force of Will"
                },
                {
                    "count": 2,
                    "name": "Inquisition of Kozilek"
                },
                {
                    "count": 4,
                    "name": "Ponder"
                },
                {
                    "count": 2,
                    "name": "Preordain"
                },
                {
                    "count": 1,
                    "name": "Thoughtseize"
                },
                {
                    "count": 1,
                    "name": "Angrath's Rampage"
                },
                {
                    "count": 2,
                    "name": "Narset, Parter of Veils"
                },
                {
                    "count": 1,
                    "name": "Jace, the Mind Sculptor"
                },
                {
                    "count": 1,
                    "name": "Badlands"
                },
                {
                    "count": 1,
                    "name": "Bloodstained Mire"
                },
                {
                    "count": 2,
                    "name": "Island"
                },
                {
                    "count": 4,
                    "name": "Polluted Delta"
                },
                {
                    "count": 2,
                    "name": "Prismatic Vista"
                },
                {
                    "count": 4,
                    "name": "Scalding Tarn"
                },
                {
                    "count": 2,
                    "name": "Snow-Covered Island"
                },
                {
                    "count": 1,
                    "name": "Snow-Covered Mountain"
                },
                {
                    "count": 1,
                    "name": "Snow-Covered Swamp"
                },
                {
                    "count": 1,
                    "name": "Underground Sea"
                },
                {
                    "count": 1,
                    "name": "Volcanic Island"
                }
            ],
            "sideboard": [
                {
                    "count": 1,
                    "name": "Liliana's Triumph"
                },
                {
                    "count": 1,
                    "name": "Thoughtseize"
                },
                {
                    "count": 1,
                    "name": "Plague Engineer"
                },
                {
                    "count": 2,
                    "name": "Flusterstorm"
                },
                {
                    "count": 1,
                    "name": "Hydroblast"
                },
                {
                    "count": 1,
                    "name": "Nihil Spellbomb"
                },
                {
                    "count": 1,
                    "name": "Pyroblast"
                },
                {
                    "count": 2,
                    "name": "Red Elemental Blast"
                },
                {
                    "count": 2,
                    "name": "Surgical Extraction"
                },
                {
                    "count": 1,
                    "name": "Tyrant's Scorn"
                },
                {
                    "count": 2,
                    "name": "Blood Moon"
                }
            ],
            "notes": "The main focus of this deck is to control the game through a combination of removal spells, counterspells, and disruptive creatures like Dreadhorde Arcanist and True-Name Nemesis. By utilizing cards like Brainstorm, Kolaghan's Command, and Narset, Parter of Veils, the deck aims to manipulate the opponent's resources while gradually building up its own advantage. The inclusion of powerful planeswalkers like Jace, the Mind Sculptor adds another layer of control to the deck, making it difficult for opponents to mount a comeback. Ultimately, the Grixis Control archetype strives to outvalue and outlast the opponent in a game of attrition."
        },
        {
            "date": "2019-09-22",
            "player": "Irian Benedetti",
            "result": 5,
            "anchor_uri": "https://mtgtop8.com/event?e=23226&d=359711&f=LE",
            "mainboard": [
                {
                    "count": 4,
                    "name": "Stoneforge Mystic"
                },
                {
                    "count": 3,
                    "name": "Snapcaster Mage"
                },
                {
                    "count": 3,
                    "name": "True-Name Nemesis"
                },
                {
                    "count": 1,
                    "name": "Vendilion Clique"
                },
                {
                    "count": 1,
                    "name": "Batterskull"
                },
                {
                    "count": 1,
                    "name": "Umezawa's Jitte"
                },
                {
                    "count": 4,
                    "name": "Brainstorm"
                },
                {
                    "count": 4,
                    "name": "Force of Will"
                },
                {
                    "count": 1,
                    "name": "Force of Negation"
                },
                {
                    "count": 2,
                    "name": "Spell Pierce"
                },
                {
                    "count": 1,
                    "name": "Spell Snare"
                },
                {
                    "count": 4,
                    "name": "Swords to Plowshares"
                },
                {
                    "count": 4,
                    "name": "Ponder"
                },
                {
                    "count": 1,
                    "name": "Council's Judgment"
                },
                {
                    "count": 2,
                    "name": "Back to Basics"
                },
                {
                    "count": 1,
                    "name": "Narset, Parter of Veils"
                },
                {
                    "count": 2,
                    "name": "Jace, the Mind Sculptor"
                },
                {
                    "count": 1,
                    "name": "Teferi, Time Raveler"
                },
                {
                    "count": 4,
                    "name": "Flooded Strand"
                },
                {
                    "count": 4,
                    "name": "Prismatic Vista"
                },
                {
                    "count": 6,
                    "name": "Island"
                },
                {
                    "count": 2,
                    "name": "Tundra"
                },
                {
                    "count": 1,
                    "name": "Karakas"
                },
                {
                    "count": 2,
                    "name": "Plains"
                },
                {
                    "count": 1,
                    "name": "Scalding Tarn"
                }
            ],
            "sideboard": [
                {
                    "count": 1,
                    "name": "Vendilion Clique"
                },
                {
                    "count": 1,
                    "name": "Council's Judgment"
                },
                {
                    "count": 1,
                    "name": "Dovin's Veto"
                },
                {
                    "count": 1,
                    "name": "Gideon, Ally of Zendikar"
                },
                {
                    "count": 1,
                    "name": "Disenchant"
                },
                {
                    "count": 1,
                    "name": "Nahiri, the Lithomancer"
                },
                {
                    "count": 1,
                    "name": "Celestial Purge"
                },
                {
                    "count": 1,
                    "name": "Path to Exile"
                },
                {
                    "count": 2,
                    "name": "Surgical Extraction"
                },
                {
                    "count": 2,
                    "name": "Flusterstorm"
                },
                {
                    "count": 1,
                    "name": "Supreme Verdict"
                },
                {
                    "count": 1,
                    "name": "Hydroblast"
                },
                {
                    "count": 1,
                    "name": "Palace Jailer"
                }
            ],
            "notes": "The primary strategy of this deck is to control the game by using powerful spells like Force of Will, Swords to Plowshares, and counter spells like Spell Pierce and Spell Snare. The deck also utilizes creatures such as Stoneforge Mystic, True-Name Nemesis, and Vendilion Clique to apply pressure and disrupt the opponent's game plan. The inclusion of equipment like Batterskull and Umezawa's Jitte provides additional versatility and threat. Overall, this deck aims to outvalue and outmaneuver the opponent through efficient card selection and powerful control elements."
        },
        {
            "date": "2019-09-22",
            "player": "Caversazio Carlo",
            "result": 5,
            "anchor_uri": "https://mtgtop8.com/event?e=23226&d=359710&f=LE",
            "mainboard": [
                {
                    "count": 4,
                    "name": "Lotus Petal"
                },
                {
                    "count": 4,
                    "name": "Lion's Eye Diamond"
                },
                {
                    "count": 4,
                    "name": "Brainstorm"
                },
                {
                    "count": 4,
                    "name": "Dark Ritual"
                },
                {
                    "count": 4,
                    "name": "Cabal Ritual"
                },
                {
                    "count": 1,
                    "name": "Ad Nauseam"
                },
                {
                    "count": 4,
                    "name": "Ponder"
                },
                {
                    "count": 4,
                    "name": "Preordain"
                },
                {
                    "count": 4,
                    "name": "Thoughtseize"
                },
                {
                    "count": 4,
                    "name": "Duress"
                },
                {
                    "count": 4,
                    "name": "Infernal Tutor"
                },
                {
                    "count": 2,
                    "name": "Past in Flames"
                },
                {
                    "count": 1,
                    "name": "Dark Petition"
                },
                {
                    "count": 1,
                    "name": "Tendrils of Agony"
                },
                {
                    "count": 4,
                    "name": "Polluted Delta"
                },
                {
                    "count": 4,
                    "name": "Misty Rainforest"
                },
                {
                    "count": 2,
                    "name": "Underground Sea"
                },
                {
                    "count": 1,
                    "name": "Volcanic Island"
                },
                {
                    "count": 1,
                    "name": "Tropical Island"
                },
                {
                    "count": 1,
                    "name": "Bayou"
                },
                {
                    "count": 1,
                    "name": "Island"
                },
                {
                    "count": 1,
                    "name": "Swamp"
                }
            ],
            "sideboard": [
                {
                    "count": 1,
                    "name": "Tendrils of Agony"
                },
                {
                    "count": 2,
                    "name": "Abrupt Decay"
                },
                {
                    "count": 2,
                    "name": "Veil of Summer"
                },
                {
                    "count": 2,
                    "name": "Flusterstorm"
                },
                {
                    "count": 2,
                    "name": "Fatal Push"
                },
                {
                    "count": 2,
                    "name": "Echoing Truth"
                },
                {
                    "count": 2,
                    "name": "Hurkyl's Recall"
                },
                {
                    "count": 1,
                    "name": "Chain of Vapor"
                },
                {
                    "count": 1,
                    "name": "Empty the Warrens"
                }
            ],
            "notes": "The main concept of this deck is to quickly amass the necessary resources to cast a large number of spells in a single turn to generate a lethal storm count. The deck focuses on using efficient card draw, mana acceleration, and disruption spells to set up for a game-winning Tendrils of Agony or Ad Nauseam. The deck also utilizes graveyard recursion with Past in Flames to maximize its storm count potential. The mana base includes a mix of fetch lands and dual lands to ensure consistent mana fixing."
        }
    ],
    "rounds": [],
    "standings": []
}