{
    "tournament": {
        "date": "2024-10-13",
        "name": "MTGO Challenge 64",
        "url": "https://mtgtop8.com/event?e=60453",
        "format": "Modern",
        "players": 65
    },
    "decks": [
        {
            "date": "2024-10-13",
            "player": "Nammersquats",
            "result": 1,
            "anchor_uri": "https://mtgtop8.com/event?e=60453&d=653992&f=MO",
            "mainboard": [
                {
                    "count": 2,
                    "name": "Galvanic Discharge"
                },
                {
                    "count": 2,
                    "name": "Blood Moon"
                },
                {
                    "count": 3,
                    "name": "The One Ring"
                },
                {
                    "count": 3,
                    "name": "Lightning Bolt"
                },
                {
                    "count": 3,
                    "name": "Goblin Bombardment"
                },
                {
                    "count": 4,
                    "name": "Static Prison"
                },
                {
                    "count": 4,
                    "name": "Amped Raptor"
                },
                {
                    "count": 4,
                    "name": "Guide of Souls"
                },
                {
                    "count": 4,
                    "name": "Ocelot Pride"
                },
                {
                    "count": 4,
                    "name": "Phlage, Titan of Fire's Fury"
                },
                {
                    "count": 4,
                    "name": "Ajani, Nacatl Pariah"
                },
                {
                    "count": 1,
                    "name": "Mountain"
                },
                {
                    "count": 2,
                    "name": "Arena of Glory"
                },
                {
                    "count": 2,
                    "name": "Elegant Parlor"
                },
                {
                    "count": 3,
                    "name": "Aether Hub"
                },
                {
                    "count": 3,
                    "name": "Plains"
                },
                {
                    "count": 4,
                    "name": "Arid Mesa"
                },
                {
                    "count": 4,
                    "name": "Marsh Flats"
                },
                {
                    "count": 4,
                    "name": "Sacred Foundry"
                }
            ],
            "sideboard": [
                {
                    "count": 2,
                    "name": "Thraben Charm"
                },
                {
                    "count": 2,
                    "name": "Disruptor Flute"
                },
                {
                    "count": 3,
                    "name": "Magebane Lizard"
                },
                {
                    "count": 2,
                    "name": "Fear, Fire, Foes!"
                },
                {
                    "count": 2,
                    "name": "Orim's Chant"
                },
                {
                    "count": 3,
                    "name": "Obsidian Charmaw"
                },
                {
                    "count": 1,
                    "name": "Jegantha, the Wellspring"
                }
            ],
            "notes": "The main concept of this Boros Aggro deck is to quickly overwhelm the opponent with aggressive creatures and burn spells, while utilizing cards like Static Prison and Blood Moon to disrupt their game plan. Jegantha, the Wellspring serves as a powerful companion option, providing additional value and flexibility. The deck focuses on efficient creatures like Guide of Souls and Amped Raptor, supported by burn spells like Lightning Bolt. Ocelot Pride and Phlage, Titan of Fire's Fury offer additional threats, while Ajani, Nacatl Pariah provides utility and synergy with the creature-heavy strategy. The mana base is optimized for consistency and speed."
        },
        {
            "date": "2024-10-13",
            "player": "Ingrish",
            "result": 2,
            "anchor_uri": "https://mtgtop8.com/event?e=60453&d=653993&f=MO",
            "mainboard": [
                {
                    "count": 3,
                    "name": "Aether Hub"
                },
                {
                    "count": 4,
                    "name": "Ajani, Nacatl Pariah"
                },
                {
                    "count": 4,
                    "name": "Amped Raptor"
                },
                {
                    "count": 2,
                    "name": "Arena of Glory"
                },
                {
                    "count": 4,
                    "name": "Arid Mesa"
                },
                {
                    "count": 2,
                    "name": "Elegant Parlor"
                },
                {
                    "count": 2,
                    "name": "Galvanic Discharge"
                },
                {
                    "count": 3,
                    "name": "The One Ring"
                },
                {
                    "count": 4,
                    "name": "Guide of Souls"
                },
                {
                    "count": 1,
                    "name": "Mountain"
                },
                {
                    "count": 4,
                    "name": "Ocelot Pride"
                },
                {
                    "count": 4,
                    "name": "Phlage, Titan of Fire's Fury"
                },
                {
                    "count": 3,
                    "name": "Plains"
                },
                {
                    "count": 3,
                    "name": "Ragavan, Nimble Pilferer"
                },
                {
                    "count": 3,
                    "name": "Lightning Bolt"
                },
                {
                    "count": 4,
                    "name": "Static Prison"
                },
                {
                    "count": 2,
                    "name": "Goblin Bombardment"
                },
                {
                    "count": 4,
                    "name": "Marsh Flats"
                },
                {
                    "count": 4,
                    "name": "Sacred Foundry"
                }
            ],
            "sideboard": [
                {
                    "count": 1,
                    "name": "The One Ring"
                },
                {
                    "count": 3,
                    "name": "Blood Moon"
                },
                {
                    "count": 2,
                    "name": "Damping Sphere"
                },
                {
                    "count": 2,
                    "name": "Reprieve"
                },
                {
                    "count": 1,
                    "name": "Jegantha, the Wellspring"
                },
                {
                    "count": 1,
                    "name": "Orim's Chant"
                },
                {
                    "count": 2,
                    "name": "Thraben Charm"
                },
                {
                    "count": 1,
                    "name": "Untimely Malfunction"
                },
                {
                    "count": 2,
                    "name": "Fear, Fire, Foes!"
                }
            ],
            "notes": ""
        },
        {
            "date": "2024-10-13",
            "player": "oOMegaGenesis",
            "result": 3,
            "anchor_uri": "https://mtgtop8.com/event?e=60453&d=653996&f=MO",
            "mainboard": [
                {
                    "count": 3,
                    "name": "Aether Hub"
                },
                {
                    "count": 4,
                    "name": "Ajani, Nacatl Pariah"
                },
                {
                    "count": 4,
                    "name": "Amped Raptor"
                },
                {
                    "count": 2,
                    "name": "Arena of Glory"
                },
                {
                    "count": 3,
                    "name": "The One Ring"
                },
                {
                    "count": 2,
                    "name": "Elegant Parlor"
                },
                {
                    "count": 2,
                    "name": "Galvanic Discharge"
                },
                {
                    "count": 2,
                    "name": "Goblin Bombardment"
                },
                {
                    "count": 4,
                    "name": "Guide of Souls"
                },
                {
                    "count": 3,
                    "name": "Lightning Bolt"
                },
                {
                    "count": 3,
                    "name": "Plains"
                },
                {
                    "count": 1,
                    "name": "Mountain"
                },
                {
                    "count": 4,
                    "name": "Ocelot Pride"
                },
                {
                    "count": 4,
                    "name": "Phlage, Titan of Fire's Fury"
                },
                {
                    "count": 4,
                    "name": "Marsh Flats"
                },
                {
                    "count": 3,
                    "name": "Ragavan, Nimble Pilferer"
                },
                {
                    "count": 4,
                    "name": "Sacred Foundry"
                },
                {
                    "count": 4,
                    "name": "Static Prison"
                },
                {
                    "count": 4,
                    "name": "Arid Mesa"
                }
            ],
            "sideboard": [
                {
                    "count": 1,
                    "name": "The One Ring"
                },
                {
                    "count": 2,
                    "name": "Damping Sphere"
                },
                {
                    "count": 2,
                    "name": "Reprieve"
                },
                {
                    "count": 1,
                    "name": "Orim's Chant"
                },
                {
                    "count": 1,
                    "name": "Jegantha, the Wellspring"
                },
                {
                    "count": 2,
                    "name": "Fear, Fire, Foes!"
                },
                {
                    "count": 3,
                    "name": "Blood Moon"
                },
                {
                    "count": 2,
                    "name": "Thraben Charm"
                },
                {
                    "count": 1,
                    "name": "Untimely Malfunction"
                }
            ],
            "notes": ""
        },
        {
            "date": "2024-10-13",
            "player": "twiztidg",
            "result": 3,
            "anchor_uri": "https://mtgtop8.com/event?e=60453&d=653988&f=MO",
            "mainboard": [
                {
                    "count": 4,
                    "name": "Goblin Charbelcher"
                },
                {
                    "count": 2,
                    "name": "Spell Snare"
                },
                {
                    "count": 4,
                    "name": "Hydroelectric Specimen"
                },
                {
                    "count": 4,
                    "name": "Lotus Bloom"
                },
                {
                    "count": 4,
                    "name": "Sea Gate Restoration"
                },
                {
                    "count": 4,
                    "name": "Sink into Stupor"
                },
                {
                    "count": 3,
                    "name": "Waterlogged Teachings"
                },
                {
                    "count": 4,
                    "name": "Whir of Invention"
                },
                {
                    "count": 4,
                    "name": "Tameshi, Reality Architect"
                },
                {
                    "count": 4,
                    "name": "Counterspell"
                },
                {
                    "count": 4,
                    "name": "Preordain"
                },
                {
                    "count": 3,
                    "name": "Unable to Scream"
                },
                {
                    "count": 4,
                    "name": "Silundi Vision"
                },
                {
                    "count": 4,
                    "name": "Beyeen Veil"
                },
                {
                    "count": 1,
                    "name": "Jwari Disruption"
                },
                {
                    "count": 4,
                    "name": "Disrupting Shoal"
                },
                {
                    "count": 3,
                    "name": "Force of Negation"
                }
            ],
            "sideboard": [
                {
                    "count": 1,
                    "name": "Spell Snare"
                },
                {
                    "count": 1,
                    "name": "Unable to Scream"
                },
                {
                    "count": 2,
                    "name": "Harbinger of the Seas"
                },
                {
                    "count": 3,
                    "name": "Consign to Memory"
                },
                {
                    "count": 3,
                    "name": "Mystical Dispute"
                },
                {
                    "count": 2,
                    "name": "Stern Scolding"
                },
                {
                    "count": 3,
                    "name": "Into the Flood Maw"
                }
            ],
            "notes": "The deck focuses on assembling a powerful combo involving Goblin Charbelcher and Hydroelectric Specimen to deal massive damage to the opponent. It utilizes a variety of counterspells and card draw to protect the combo pieces and ensure a smooth execution. The deck does not rely on traditional land cards, instead opting for mana-producing artifacts and spells. The key strategy is to disrupt the opponent's game plan while setting up the combo pieces to win the game quickly and decisively."
        },
        {
            "date": "2024-10-13",
            "player": "MC_amp2267",
            "result": 5,
            "anchor_uri": "https://mtgtop8.com/event?e=60453&d=653998&f=MO",
            "mainboard": [
                {
                    "count": 4,
                    "name": "Leyline of the Guildpact"
                },
                {
                    "count": 4,
                    "name": "Leyline Binding"
                },
                {
                    "count": 4,
                    "name": "Arid Mesa"
                },
                {
                    "count": 1,
                    "name": "Mountain"
                },
                {
                    "count": 4,
                    "name": "Scion of Draco"
                },
                {
                    "count": 4,
                    "name": "Flooded Strand"
                },
                {
                    "count": 4,
                    "name": "Wooded Foothills"
                },
                {
                    "count": 1,
                    "name": "Steam Vents"
                },
                {
                    "count": 1,
                    "name": "Sacred Foundry"
                },
                {
                    "count": 1,
                    "name": "Blood Crypt"
                },
                {
                    "count": 4,
                    "name": "Lightning Bolt"
                },
                {
                    "count": 1,
                    "name": "Temple Garden"
                },
                {
                    "count": 4,
                    "name": "Territorial Kavu"
                },
                {
                    "count": 3,
                    "name": "Phlage, Titan of Fire's Fury"
                },
                {
                    "count": 4,
                    "name": "Stubborn Denial"
                },
                {
                    "count": 4,
                    "name": "Orcish Bowmasters"
                },
                {
                    "count": 4,
                    "name": "Tribal Flames"
                },
                {
                    "count": 4,
                    "name": "Ragavan, Nimble Pilferer"
                },
                {
                    "count": 1,
                    "name": "Indatha Triome"
                },
                {
                    "count": 1,
                    "name": "Thundering Falls"
                },
                {
                    "count": 1,
                    "name": "Breeding Pool"
                },
                {
                    "count": 1,
                    "name": "Arena of Glory"
                }
            ],
            "sideboard": [
                {
                    "count": 3,
                    "name": "Mystical Dispute"
                },
                {
                    "count": 1,
                    "name": "Jegantha, the Wellspring"
                },
                {
                    "count": 2,
                    "name": "Damping Sphere"
                },
                {
                    "count": 3,
                    "name": "Pyroclasm"
                },
                {
                    "count": 2,
                    "name": "Pick Your Poison"
                },
                {
                    "count": 4,
                    "name": "Consign to Memory"
                }
            ],
            "notes": "This aggro deck focuses on playing powerful multicolored creatures and spells to quickly overwhelm the opponent. Using Leylines to control the board and Leyline of the Guildpact to pump up creatures, the deck aims to deal damage efficiently with cards like Ragavan, Nimble Pilferer and Tribal Flames. The inclusion of Jegantha, the Wellspring as a companion ensures access to additional mana and provides flexibility in the deck's composition. With a mix of aggressive creatures and burn spells, this deck aims to close out games swiftly before the opponent can stabilize."
        },
        {
            "date": "2024-10-13",
            "player": "Statuskrow",
            "result": 5,
            "anchor_uri": "https://mtgtop8.com/event?e=60453&d=653987&f=MO",
            "mainboard": [
                {
                    "count": 3,
                    "name": "Aether Hub"
                },
                {
                    "count": 4,
                    "name": "Ajani, Nacatl Pariah"
                },
                {
                    "count": 4,
                    "name": "Marsh Flats"
                },
                {
                    "count": 4,
                    "name": "Phlage, Titan of Fire's Fury"
                },
                {
                    "count": 4,
                    "name": "Ocelot Pride"
                },
                {
                    "count": 2,
                    "name": "Elegant Parlor"
                },
                {
                    "count": 2,
                    "name": "Galvanic Discharge"
                },
                {
                    "count": 1,
                    "name": "Mountain"
                },
                {
                    "count": 4,
                    "name": "Arid Mesa"
                },
                {
                    "count": 4,
                    "name": "Guide of Souls"
                },
                {
                    "count": 4,
                    "name": "Sacred Foundry"
                },
                {
                    "count": 3,
                    "name": "The One Ring"
                },
                {
                    "count": 2,
                    "name": "Arena of Glory"
                },
                {
                    "count": 4,
                    "name": "Amped Raptor"
                },
                {
                    "count": 4,
                    "name": "Static Prison"
                },
                {
                    "count": 3,
                    "name": "Ragavan, Nimble Pilferer"
                },
                {
                    "count": 2,
                    "name": "Goblin Bombardment"
                },
                {
                    "count": 3,
                    "name": "Plains"
                },
                {
                    "count": 3,
                    "name": "Lightning Bolt"
                }
            ],
            "sideboard": [
                {
                    "count": 1,
                    "name": "The One Ring"
                },
                {
                    "count": 1,
                    "name": "Jegantha, the Wellspring"
                },
                {
                    "count": 2,
                    "name": "Damping Sphere"
                },
                {
                    "count": 2,
                    "name": "Thraben Charm"
                },
                {
                    "count": 1,
                    "name": "Orim's Chant"
                },
                {
                    "count": 2,
                    "name": "Reprieve"
                },
                {
                    "count": 2,
                    "name": "Fear, Fire, Foes!"
                },
                {
                    "count": 1,
                    "name": "Untimely Malfunction"
                },
                {
                    "count": 3,
                    "name": "Blood Moon"
                }
            ],
            "notes": "The Boros Aggro deck focuses on fast and aggressive creature attacks, supported by burn spells and disruptive effects. It aims to quickly overwhelm the opponent with strong creatures and direct damage, utilizing cards like Ajani, Nacatl Pariah and Lightning Bolt to clear the way for attacks. The inclusion of Jegantha, the Wellspring as a companion adds flexibility and additional mana ramp potential. The deck is designed to apply constant pressure and end the game swiftly before the opponent can establish a strong defense."
        },
        {
            "date": "2024-10-13",
            "player": "John_Cabral",
            "result": 5,
            "anchor_uri": "https://mtgtop8.com/event?e=60453&d=654002&f=MO",
            "mainboard": [
                {
                    "count": 2,
                    "name": "Aether Hub"
                },
                {
                    "count": 1,
                    "name": "Mountain"
                },
                {
                    "count": 4,
                    "name": "Ocelot Pride"
                },
                {
                    "count": 2,
                    "name": "Elegant Parlor"
                },
                {
                    "count": 2,
                    "name": "Galvanic Discharge"
                },
                {
                    "count": 2,
                    "name": "Arena of Glory"
                },
                {
                    "count": 4,
                    "name": "Guide of Souls"
                },
                {
                    "count": 2,
                    "name": "Goblin Bombardment"
                },
                {
                    "count": 3,
                    "name": "Lightning Bolt"
                },
                {
                    "count": 4,
                    "name": "Marsh Flats"
                },
                {
                    "count": 3,
                    "name": "Phlage, Titan of Fire's Fury"
                },
                {
                    "count": 4,
                    "name": "Ragavan, Nimble Pilferer"
                },
                {
                    "count": 4,
                    "name": "Amped Raptor"
                },
                {
                    "count": 3,
                    "name": "Plains"
                },
                {
                    "count": 4,
                    "name": "Sacred Foundry"
                },
                {
                    "count": 4,
                    "name": "Arid Mesa"
                },
                {
                    "count": 2,
                    "name": "Blood Moon"
                },
                {
                    "count": 4,
                    "name": "Ajani, Nacatl Pariah"
                },
                {
                    "count": 2,
                    "name": "The One Ring"
                },
                {
                    "count": 4,
                    "name": "Static Prison"
                }
            ],
            "sideboard": [
                {
                    "count": 1,
                    "name": "Damping Sphere"
                },
                {
                    "count": 1,
                    "name": "Jegantha, the Wellspring"
                },
                {
                    "count": 4,
                    "name": "Obsidian Charmaw"
                },
                {
                    "count": 1,
                    "name": "Reprieve"
                },
                {
                    "count": 2,
                    "name": "Suncleanser"
                },
                {
                    "count": 1,
                    "name": "Drannith Magistrate"
                },
                {
                    "count": 3,
                    "name": "Orim's Chant"
                },
                {
                    "count": 2,
                    "name": "Thraben Charm"
                }
            ],
            "notes": ""
        },
        {
            "date": "2024-10-13",
            "player": "Furstenberger",
            "result": 5,
            "anchor_uri": "https://mtgtop8.com/event?e=60453&d=653990&f=MO",
            "mainboard": [
                {
                    "count": 4,
                    "name": "Thundertrap Trainer"
                },
                {
                    "count": 4,
                    "name": "Fallaji Archaeologist"
                },
                {
                    "count": 4,
                    "name": "Flare of Denial"
                },
                {
                    "count": 4,
                    "name": "Goblin Charbelcher"
                },
                {
                    "count": 4,
                    "name": "Hydroelectric Specimen"
                },
                {
                    "count": 4,
                    "name": "Disrupting Shoal"
                },
                {
                    "count": 1,
                    "name": "Subtlety"
                },
                {
                    "count": 4,
                    "name": "Sea Gate Restoration"
                },
                {
                    "count": 4,
                    "name": "Sink into Stupor"
                },
                {
                    "count": 4,
                    "name": "Suppression Ray"
                },
                {
                    "count": 3,
                    "name": "Tameshi, Reality Architect"
                },
                {
                    "count": 4,
                    "name": "Beyeen Veil"
                },
                {
                    "count": 4,
                    "name": "Whir of Invention"
                },
                {
                    "count": 4,
                    "name": "Jwari Disruption"
                },
                {
                    "count": 1,
                    "name": "Commandeer"
                },
                {
                    "count": 4,
                    "name": "Lotus Bloom"
                },
                {
                    "count": 3,
                    "name": "Pact of Negation"
                }
            ],
            "sideboard": [
                {
                    "count": 1,
                    "name": "Subtlety"
                },
                {
                    "count": 1,
                    "name": "Commandeer"
                },
                {
                    "count": 2,
                    "name": "Consign to Memory"
                },
                {
                    "count": 2,
                    "name": "Mystical Dispute"
                },
                {
                    "count": 1,
                    "name": "Force of Negation"
                },
                {
                    "count": 2,
                    "name": "Harbinger of the Seas"
                },
                {
                    "count": 4,
                    "name": "Unable to Scream"
                },
                {
                    "count": 2,
                    "name": "Spell Snare"
                }
            ],
            "notes": "The deck relies on a fast and powerful combo using cards like Thundertrap Trainer, Goblin Charbelcher, and Hydroelectric Specimen to win the game quickly without needing many lands. It also includes countermagic and disruptive spells like Flare of Denial and Disrupting Shoal to protect the combo pieces. The deck aims to manipulate the board and disrupt the opponent's strategy while assembling its own combo pieces to secure victory. Additionally, cards like Whir of Invention and Beyeen Veil provide additional versatility and control options to outmaneuver opponents in a Modern 1 vs 1 format."
        },
        {
            "date": "2024-10-13",
            "player": "ManUFan",
            "result": 9,
            "anchor_uri": "https://mtgtop8.com/event?e=60453&d=653991&f=MO",
            "mainboard": [
                {
                    "count": 4,
                    "name": "Arid Mesa"
                },
                {
                    "count": 4,
                    "name": "Ajani, Nacatl Pariah"
                },
                {
                    "count": 4,
                    "name": "Guide of Souls"
                },
                {
                    "count": 4,
                    "name": "Phlage, Titan of Fire's Fury"
                },
                {
                    "count": 2,
                    "name": "Galvanic Discharge"
                },
                {
                    "count": 4,
                    "name": "Amped Raptor"
                },
                {
                    "count": 3,
                    "name": "Static Prison"
                },
                {
                    "count": 2,
                    "name": "Blood Moon"
                },
                {
                    "count": 4,
                    "name": "Marsh Flats"
                },
                {
                    "count": 2,
                    "name": "Goblin Bombardment"
                },
                {
                    "count": 1,
                    "name": "Mountain"
                },
                {
                    "count": 2,
                    "name": "Aether Hub"
                },
                {
                    "count": 4,
                    "name": "Ocelot Pride"
                },
                {
                    "count": 2,
                    "name": "Arena of Glory"
                },
                {
                    "count": 3,
                    "name": "Plains"
                },
                {
                    "count": 3,
                    "name": "Ragavan, Nimble Pilferer"
                },
                {
                    "count": 1,
                    "name": "Exorcise"
                },
                {
                    "count": 4,
                    "name": "Sacred Foundry"
                },
                {
                    "count": 3,
                    "name": "Lightning Bolt"
                },
                {
                    "count": 2,
                    "name": "The One Ring"
                },
                {
                    "count": 2,
                    "name": "Elegant Parlor"
                }
            ],
            "sideboard": [
                {
                    "count": 1,
                    "name": "Blood Moon"
                },
                {
                    "count": 1,
                    "name": "Exorcise"
                },
                {
                    "count": 2,
                    "name": "The One Ring"
                },
                {
                    "count": 2,
                    "name": "Orim's Chant"
                },
                {
                    "count": 1,
                    "name": "Jegantha, the Wellspring"
                },
                {
                    "count": 2,
                    "name": "Magebane Lizard"
                },
                {
                    "count": 2,
                    "name": "Fear, Fire, Foes!"
                },
                {
                    "count": 2,
                    "name": "Thraben Charm"
                },
                {
                    "count": 2,
                    "name": "Damping Sphere"
                }
            ],
            "notes": ""
        },
        {
            "date": "2024-10-13",
            "player": "gazmon48",
            "result": 10,
            "anchor_uri": "https://mtgtop8.com/event?e=60453&d=653995&f=MO",
            "mainboard": [
                {
                    "count": 3,
                    "name": "Aether Hub"
                },
                {
                    "count": 4,
                    "name": "Ajani, Nacatl Pariah"
                },
                {
                    "count": 4,
                    "name": "Amped Raptor"
                },
                {
                    "count": 2,
                    "name": "Arena of Glory"
                },
                {
                    "count": 4,
                    "name": "Arid Mesa"
                },
                {
                    "count": 2,
                    "name": "Elegant Parlor"
                },
                {
                    "count": 2,
                    "name": "Galvanic Discharge"
                },
                {
                    "count": 3,
                    "name": "Plains"
                },
                {
                    "count": 4,
                    "name": "Guide of Souls"
                },
                {
                    "count": 1,
                    "name": "Mountain"
                },
                {
                    "count": 4,
                    "name": "Marsh Flats"
                },
                {
                    "count": 4,
                    "name": "Ocelot Pride"
                },
                {
                    "count": 4,
                    "name": "Phlage, Titan of Fire's Fury"
                },
                {
                    "count": 3,
                    "name": "Lightning Bolt"
                },
                {
                    "count": 3,
                    "name": "Ragavan, Nimble Pilferer"
                },
                {
                    "count": 4,
                    "name": "Sacred Foundry"
                },
                {
                    "count": 4,
                    "name": "Static Prison"
                },
                {
                    "count": 2,
                    "name": "Goblin Bombardment"
                },
                {
                    "count": 3,
                    "name": "The One Ring"
                }
            ],
            "sideboard": [
                {
                    "count": 1,
                    "name": "The One Ring"
                },
                {
                    "count": 3,
                    "name": "Blood Moon"
                },
                {
                    "count": 2,
                    "name": "Bonecrusher Giant"
                },
                {
                    "count": 1,
                    "name": "Damping Sphere"
                },
                {
                    "count": 1,
                    "name": "Drannith Magistrate"
                },
                {
                    "count": 1,
                    "name": "Jegantha, the Wellspring"
                },
                {
                    "count": 1,
                    "name": "Magebane Lizard"
                },
                {
                    "count": 2,
                    "name": "Orim's Chant"
                },
                {
                    "count": 1,
                    "name": "Reprieve"
                },
                {
                    "count": 2,
                    "name": "Thraben Charm"
                }
            ],
            "notes": ""
        },
        {
            "date": "2024-10-13",
            "player": "internetsurfer09",
            "result": 11,
            "anchor_uri": "https://mtgtop8.com/event?e=60453&d=653989&f=MO",
            "mainboard": [
                {
                    "count": 4,
                    "name": "Ajani, Nacatl Pariah"
                },
                {
                    "count": 4,
                    "name": "Amped Raptor"
                },
                {
                    "count": 3,
                    "name": "Aether Hub"
                },
                {
                    "count": 1,
                    "name": "Goblin Bombardment"
                },
                {
                    "count": 2,
                    "name": "Plains"
                },
                {
                    "count": 2,
                    "name": "Flooded Strand"
                },
                {
                    "count": 4,
                    "name": "Arid Mesa"
                },
                {
                    "count": 3,
                    "name": "Galvanic Discharge"
                },
                {
                    "count": 4,
                    "name": "Guide of Souls"
                },
                {
                    "count": 1,
                    "name": "Marsh Flats"
                },
                {
                    "count": 2,
                    "name": "Elegant Parlor"
                },
                {
                    "count": 4,
                    "name": "Phlage, Titan of Fire's Fury"
                },
                {
                    "count": 2,
                    "name": "Arena of Glory"
                },
                {
                    "count": 4,
                    "name": "Static Prison"
                },
                {
                    "count": 1,
                    "name": "Windswept Heath"
                },
                {
                    "count": 4,
                    "name": "Ocelot Pride"
                },
                {
                    "count": 1,
                    "name": "Mountain"
                },
                {
                    "count": 4,
                    "name": "Sacred Foundry"
                },
                {
                    "count": 3,
                    "name": "Ragavan, Nimble Pilferer"
                },
                {
                    "count": 2,
                    "name": "The One Ring"
                },
                {
                    "count": 1,
                    "name": "Blood Moon"
                },
                {
                    "count": 4,
                    "name": "Lightning Bolt"
                }
            ],
            "sideboard": [
                {
                    "count": 1,
                    "name": "The One Ring"
                },
                {
                    "count": 4,
                    "name": "Obsidian Charmaw"
                },
                {
                    "count": 1,
                    "name": "Jegantha, the Wellspring"
                },
                {
                    "count": 2,
                    "name": "Suncleanser"
                },
                {
                    "count": 2,
                    "name": "Fear, Fire, Foes!"
                },
                {
                    "count": 1,
                    "name": "Damping Sphere"
                },
                {
                    "count": 2,
                    "name": "Thraben Charm"
                },
                {
                    "count": 1,
                    "name": "Unlicensed Hearse"
                },
                {
                    "count": 1,
                    "name": "Surgical Extraction"
                }
            ],
            "notes": ""
        },
        {
            "date": "2024-10-13",
            "player": "ChimmyNorbit",
            "result": 12,
            "anchor_uri": "https://mtgtop8.com/event?e=60453&d=654001&f=MO",
            "mainboard": [
                {
                    "count": 1,
                    "name": "Arena of Glory"
                },
                {
                    "count": 4,
                    "name": "Fear of Missing Out"
                },
                {
                    "count": 1,
                    "name": "Swamp"
                },
                {
                    "count": 4,
                    "name": "Street Wraith"
                },
                {
                    "count": 4,
                    "name": "Burning Inquiry"
                },
                {
                    "count": 4,
                    "name": "Detective's Phoenix"
                },
                {
                    "count": 2,
                    "name": "Mountain"
                },
                {
                    "count": 2,
                    "name": "Marsh Flats"
                },
                {
                    "count": 2,
                    "name": "Tarfire"
                },
                {
                    "count": 2,
                    "name": "Goblin Lore"
                },
                {
                    "count": 4,
                    "name": "Hollow One"
                },
                {
                    "count": 4,
                    "name": "Dragon's Rage Channeler"
                },
                {
                    "count": 2,
                    "name": "Fatal Push"
                },
                {
                    "count": 4,
                    "name": "Orcish Bowmasters"
                },
                {
                    "count": 4,
                    "name": "Nethergoyf"
                },
                {
                    "count": 4,
                    "name": "Bloodstained Mire"
                },
                {
                    "count": 1,
                    "name": "Raucous Theater"
                },
                {
                    "count": 3,
                    "name": "Blood Crypt"
                },
                {
                    "count": 4,
                    "name": "Mishra's Bauble"
                },
                {
                    "count": 2,
                    "name": "Blackcleave Cliffs"
                },
                {
                    "count": 2,
                    "name": "Wooded Foothills"
                }
            ],
            "sideboard": [
                {
                    "count": 4,
                    "name": "Thoughtseize"
                },
                {
                    "count": 4,
                    "name": "Rough/Tumble"
                },
                {
                    "count": 3,
                    "name": "Blood Moon"
                },
                {
                    "count": 4,
                    "name": "Leyline of the Void"
                }
            ],
            "notes": "The deck focuses on quickly filling up the graveyard with cards like Street Wraith, Burning Inquiry, and Goblin Lore in order to cast powerful creatures like Hollow One and Nethergoyf for free or at a reduced cost. Detective's Phoenix and Dragon's Rage Channeler provide additional threats and card advantage. The deck also includes removal spells like Fatal Push and Tarfire to deal with opposing threats. The mana base is optimized for consistency and speed, allowing the deck to put pressure on the opponent early in the game."
        },
        {
            "date": "2024-10-13",
            "player": "toothymtg",
            "result": 13,
            "anchor_uri": "https://mtgtop8.com/event?e=60453&d=654000&f=MO",
            "mainboard": [
                {
                    "count": 2,
                    "name": "Goblin Bombardment"
                },
                {
                    "count": 2,
                    "name": "Galvanic Discharge"
                },
                {
                    "count": 3,
                    "name": "The One Ring"
                },
                {
                    "count": 4,
                    "name": "Static Prison"
                },
                {
                    "count": 4,
                    "name": "Lightning Bolt"
                },
                {
                    "count": 2,
                    "name": "Ragavan, Nimble Pilferer"
                },
                {
                    "count": 4,
                    "name": "Guide of Souls"
                },
                {
                    "count": 4,
                    "name": "Ocelot Pride"
                },
                {
                    "count": 4,
                    "name": "Amped Raptor"
                },
                {
                    "count": 4,
                    "name": "Phlage, Titan of Fire's Fury"
                },
                {
                    "count": 4,
                    "name": "Ajani, Nacatl Pariah"
                },
                {
                    "count": 1,
                    "name": "Mountain"
                },
                {
                    "count": 2,
                    "name": "Aether Hub"
                },
                {
                    "count": 2,
                    "name": "Arena of Glory"
                },
                {
                    "count": 2,
                    "name": "Elegant Parlor"
                },
                {
                    "count": 3,
                    "name": "Sacred Foundry"
                },
                {
                    "count": 3,
                    "name": "Flooded Strand"
                },
                {
                    "count": 3,
                    "name": "Windswept Heath"
                },
                {
                    "count": 3,
                    "name": "Plains"
                },
                {
                    "count": 4,
                    "name": "Arid Mesa"
                }
            ],
            "sideboard": [
                {
                    "count": 2,
                    "name": "Thraben Charm"
                },
                {
                    "count": 2,
                    "name": "Fear, Fire, Foes!"
                },
                {
                    "count": 4,
                    "name": "Obsidian Charmaw"
                },
                {
                    "count": 1,
                    "name": "Jegantha, the Wellspring"
                },
                {
                    "count": 2,
                    "name": "Suncleanser"
                },
                {
                    "count": 3,
                    "name": "Orim's Chant"
                },
                {
                    "count": 1,
                    "name": "The One Ring"
                }
            ],
            "notes": ""
        },
        {
            "date": "2024-10-13",
            "player": "Young_Shaman",
            "result": 14,
            "anchor_uri": "https://mtgtop8.com/event?e=60453&d=653994&f=MO",
            "mainboard": [
                {
                    "count": 5,
                    "name": "Forest"
                },
                {
                    "count": 1,
                    "name": "Breeding Pool"
                },
                {
                    "count": 3,
                    "name": "Devourer of Destiny"
                },
                {
                    "count": 4,
                    "name": "Emrakul, the Promised End"
                },
                {
                    "count": 4,
                    "name": "Misty Rainforest"
                },
                {
                    "count": 4,
                    "name": "Kozilek's Command"
                },
                {
                    "count": 2,
                    "name": "Ancient Stirrings"
                },
                {
                    "count": 4,
                    "name": "Malevolent Rumble"
                },
                {
                    "count": 1,
                    "name": "Shifting Woodland"
                },
                {
                    "count": 4,
                    "name": "Sowing Mycospawn"
                },
                {
                    "count": 1,
                    "name": "Stomping Ground"
                },
                {
                    "count": 1,
                    "name": "Cavern of Souls"
                },
                {
                    "count": 4,
                    "name": "Ugin's Labyrinth"
                },
                {
                    "count": 4,
                    "name": "The One Ring"
                },
                {
                    "count": 1,
                    "name": "All Is Dust"
                },
                {
                    "count": 2,
                    "name": "Talisman of Impulse"
                },
                {
                    "count": 2,
                    "name": "World Breaker"
                },
                {
                    "count": 1,
                    "name": "Commercial District"
                },
                {
                    "count": 4,
                    "name": "Eldrazi Temple"
                },
                {
                    "count": 3,
                    "name": "Kozilek's Return"
                },
                {
                    "count": 3,
                    "name": "Utopia Sprawl"
                },
                {
                    "count": 2,
                    "name": "Talisman of Curiosity"
                }
            ],
            "sideboard": [
                {
                    "count": 1,
                    "name": "World Breaker"
                },
                {
                    "count": 1,
                    "name": "Kozilek's Return"
                },
                {
                    "count": 3,
                    "name": "Consign to Memory"
                },
                {
                    "count": 2,
                    "name": "Haywire Mite"
                },
                {
                    "count": 2,
                    "name": "Trinisphere"
                },
                {
                    "count": 2,
                    "name": "Soulless Jailer"
                },
                {
                    "count": 3,
                    "name": "Flusterstorm"
                },
                {
                    "count": 1,
                    "name": "Soul-Guide Lantern"
                }
            ],
            "notes": "The deck focuses on using Eldrazi creatures to ramp up mana quickly, allowing for powerful spells like Emrakul, the Promised End and World Breaker to be cast early in the game. The control aspect comes from cards like Kozilek's Command and Malevolent Rumble, which can disrupt the opponent's strategy and clear their board. The use of Ugin's Labyrinth and The One Ring provide additional protection and card advantage. Overall, the strategy revolves around quickly ramping up mana and overwhelming the opponent with powerful Eldrazi creatures while controlling the board with disruption spells."
        },
        {
            "date": "2024-10-13",
            "player": "NathanOfTheGiltLeaf",
            "result": 15,
            "anchor_uri": "https://mtgtop8.com/event?e=60453&d=653999&f=MO",
            "mainboard": [
                {
                    "count": 4,
                    "name": "Consider"
                },
                {
                    "count": 4,
                    "name": "Dream's Grip"
                },
                {
                    "count": 4,
                    "name": "Hidden Strings"
                },
                {
                    "count": 4,
                    "name": "Lotus Field"
                },
                {
                    "count": 2,
                    "name": "Otawara, Soaring City"
                },
                {
                    "count": 4,
                    "name": "Preordain"
                },
                {
                    "count": 3,
                    "name": "Sink into Stupor"
                },
                {
                    "count": 2,
                    "name": "Twiddle"
                },
                {
                    "count": 3,
                    "name": "Underworld Breach"
                },
                {
                    "count": 4,
                    "name": "Vizier of Tumbling Sands"
                },
                {
                    "count": 4,
                    "name": "Wish"
                },
                {
                    "count": 3,
                    "name": "Island"
                },
                {
                    "count": 2,
                    "name": "Consign to Memory"
                },
                {
                    "count": 1,
                    "name": "Meticulous Archive"
                },
                {
                    "count": 3,
                    "name": "Deserted Temple"
                },
                {
                    "count": 3,
                    "name": "Expedition Map"
                },
                {
                    "count": 4,
                    "name": "Scalding Tarn"
                },
                {
                    "count": 1,
                    "name": "Hallowed Fountain"
                },
                {
                    "count": 4,
                    "name": "The One Ring"
                },
                {
                    "count": 1,
                    "name": "Thassa's Oracle"
                }
            ],
            "sideboard": [
                {
                    "count": 1,
                    "name": "Underworld Breach"
                },
                {
                    "count": 1,
                    "name": "Tome Scour"
                },
                {
                    "count": 3,
                    "name": "Into the Flood Maw"
                },
                {
                    "count": 1,
                    "name": "Jace, Wielder of Mysteries"
                },
                {
                    "count": 2,
                    "name": "Defense Grid"
                },
                {
                    "count": 2,
                    "name": "Drannith Magistrate"
                },
                {
                    "count": 3,
                    "name": "Orim's Chant"
                },
                {
                    "count": 1,
                    "name": "Temporary Lockdown"
                },
                {
                    "count": 1,
                    "name": "Strix Serenade"
                }
            ],
            "notes": "This deck focuses on utilizing Underworld Breach to create a powerful combo with Vizier of Tumbling Sands and Lotus Field to generate large amounts of mana and repeatedly cast spells from the graveyard. The deck includes cards like Wish, Consign to Memory, and Meticulous Archive to help set up the combo and dig for combo pieces. With the ability to manipulate mana and draw cards, this deck aims to quickly assemble its combo and overwhelm the opponent with a flurry of spells and abilities."
        },
        {
            "date": "2024-10-13",
            "player": "Hiro_Hsiang",
            "result": 16,
            "anchor_uri": "https://mtgtop8.com/event?e=60453&d=653997&f=MO",
            "mainboard": [
                {
                    "count": 1,
                    "name": "Sink into Stupor"
                },
                {
                    "count": 1,
                    "name": "Force of Negation"
                },
                {
                    "count": 1,
                    "name": "Shoot the Sheriff"
                },
                {
                    "count": 1,
                    "name": "Cut Down"
                },
                {
                    "count": 2,
                    "name": "Spell Pierce"
                },
                {
                    "count": 3,
                    "name": "Spell Snare"
                },
                {
                    "count": 3,
                    "name": "Consider"
                },
                {
                    "count": 4,
                    "name": "Counterspell"
                },
                {
                    "count": 4,
                    "name": "Fatal Push"
                },
                {
                    "count": 4,
                    "name": "Unearth"
                },
                {
                    "count": 4,
                    "name": "Thought Scour"
                },
                {
                    "count": 1,
                    "name": "Overlord of the Balemurk"
                },
                {
                    "count": 2,
                    "name": "Harbinger of the Seas"
                },
                {
                    "count": 3,
                    "name": "Murktide Regent"
                },
                {
                    "count": 4,
                    "name": "Abhorrent Oculus"
                },
                {
                    "count": 4,
                    "name": "Psychic Frog"
                },
                {
                    "count": 1,
                    "name": "Sunken Ruins"
                },
                {
                    "count": 1,
                    "name": "Swamp"
                },
                {
                    "count": 2,
                    "name": "Scalding Tarn"
                },
                {
                    "count": 2,
                    "name": "Gloomlake Verge"
                },
                {
                    "count": 2,
                    "name": "Undercity Sewers"
                },
                {
                    "count": 2,
                    "name": "Watery Grave"
                },
                {
                    "count": 2,
                    "name": "Island"
                },
                {
                    "count": 2,
                    "name": "Flooded Strand"
                },
                {
                    "count": 4,
                    "name": "Polluted Delta"
                }
            ],
            "sideboard": [
                {
                    "count": 1,
                    "name": "Thoughtseize"
                },
                {
                    "count": 1,
                    "name": "Surgical Extraction"
                },
                {
                    "count": 1,
                    "name": "Nihil Spellbomb"
                },
                {
                    "count": 1,
                    "name": "Damping Sphere"
                },
                {
                    "count": 1,
                    "name": "Mystical Dispute"
                },
                {
                    "count": 1,
                    "name": "Path of Peril"
                },
                {
                    "count": 4,
                    "name": "Consign to Memory"
                },
                {
                    "count": 1,
                    "name": "Disruptor Flute"
                },
                {
                    "count": 1,
                    "name": "Toxic Deluge"
                },
                {
                    "count": 2,
                    "name": "Subtlety"
                },
                {
                    "count": 1,
                    "name": "Overlord of the Balemurk"
                }
            ],
            "notes": "The deck focuses on controlling the board through a combination of counterspells, removal spells, and powerful creatures. It aims to disrupt the opponent's game plan while establishing its own threats through cards like Murktide Regent and Abhorrent Oculus. The deck's main strategy is to stall the game until it can overwhelm the opponent with its powerful creatures and control elements. The mana base is designed to support the deck's color requirements and facilitate the casting of its spells efficiently. Overall, the deck seeks to dominate the battlefield through a blend of disruption and powerful creatures."
        }
    ],
    "rounds": [],
    "standings": []
}