{
    "tournament": {
        "date": "2015-11-23",
        "name": "MTGO Pauper Premier (#9045037)",
        "url": "https://mtgtop8.com/event?e=10982",
        "format": "Pauper",
        "players": 0
    },
    "decks": [
        {
            "date": "2015-11-23",
            "player": "Mezzel",
            "result": 1,
            "anchor_uri": "https://mtgtop8.com/event?e=10982&d=262536&f=PAU",
            "mainboard": [
                {
                    "count": 4,
                    "name": "Cloud of Faeries"
                },
                {
                    "count": 4,
                    "name": "Delver of Secrets"
                },
                {
                    "count": 4,
                    "name": "Ninja of the Deep Hours"
                },
                {
                    "count": 4,
                    "name": "Spellstutter Sprite"
                },
                {
                    "count": 3,
                    "name": "Spire Golem"
                },
                {
                    "count": 3,
                    "name": "Ponder"
                },
                {
                    "count": 3,
                    "name": "Preordain"
                },
                {
                    "count": 4,
                    "name": "Counterspell"
                },
                {
                    "count": 2,
                    "name": "Deprive"
                },
                {
                    "count": 2,
                    "name": "Exclude"
                },
                {
                    "count": 2,
                    "name": "Gush"
                },
                {
                    "count": 4,
                    "name": "Snap"
                },
                {
                    "count": 2,
                    "name": "Flayer Husk"
                },
                {
                    "count": 17,
                    "name": "Island"
                },
                {
                    "count": 2,
                    "name": "Quicksand"
                }
            ],
            "sideboard": [
                {
                    "count": 3,
                    "name": "Annul"
                },
                {
                    "count": 4,
                    "name": "Coral Net"
                },
                {
                    "count": 4,
                    "name": "Hydroblast"
                },
                {
                    "count": 2,
                    "name": "Relic of Progenitus"
                },
                {
                    "count": 2,
                    "name": "Stitched Drake"
                }
            ],
            "notes": "The deck focuses on quickly deploying threats like Delver of Secrets and Ninja of the Deep Hours, supported by disruption in the form of Spellstutter Sprite and counterspells like Counterspell. The inclusion of cards like Cloud of Faeries and Gush allows for tempo plays, while also generating card advantage through bounce effects like Snap. The deck aims to maintain early pressure and then transition into a more midrange strategy with cards like Spire Golem and Flayer Husk. The mana base is streamlined with a heavy Island count to ensure consistent casting of spells."
        },
        {
            "date": "2015-11-23",
            "player": "snapcaster____mage",
            "result": 2,
            "anchor_uri": "https://mtgtop8.com/event?e=10982&d=262537&f=PAU",
            "mainboard": [
                {
                    "count": 1,
                    "name": "Echoing Decay"
                },
                {
                    "count": 2,
                    "name": "Geth's Verdict"
                },
                {
                    "count": 2,
                    "name": "Tendrils of Corruption"
                },
                {
                    "count": 1,
                    "name": "Victim of Night"
                },
                {
                    "count": 2,
                    "name": "Oubliette"
                },
                {
                    "count": 1,
                    "name": "Pestilence"
                },
                {
                    "count": 3,
                    "name": "Barren Moor"
                },
                {
                    "count": 1,
                    "name": "Bojuka Bog"
                },
                {
                    "count": 18,
                    "name": "Swamp"
                },
                {
                    "count": 4,
                    "name": "Chittering Rats"
                },
                {
                    "count": 3,
                    "name": "Cuombajj Witches"
                },
                {
                    "count": 4,
                    "name": "Gray Merchant of Asphodel"
                },
                {
                    "count": 2,
                    "name": "Gurmag Angler"
                },
                {
                    "count": 1,
                    "name": "Liliana's Specter"
                },
                {
                    "count": 4,
                    "name": "Phyrexian Rager"
                },
                {
                    "count": 3,
                    "name": "Chainer's Edict"
                },
                {
                    "count": 4,
                    "name": "Sign in Blood"
                },
                {
                    "count": 2,
                    "name": "Unearth"
                },
                {
                    "count": 2,
                    "name": "Disfigure"
                }
            ],
            "sideboard": [
                {
                    "count": 1,
                    "name": "Echoing Decay"
                },
                {
                    "count": 1,
                    "name": "Pestilence"
                },
                {
                    "count": 3,
                    "name": "Choking Sands"
                },
                {
                    "count": 2,
                    "name": "Dead Weight"
                },
                {
                    "count": 3,
                    "name": "Duress"
                },
                {
                    "count": 2,
                    "name": "Nihil Spellbomb"
                },
                {
                    "count": 1,
                    "name": "Shrivel"
                },
                {
                    "count": 2,
                    "name": "Wrench Mind"
                }
            ],
            "notes": "The main concept of this Mono Black Aggro deck is to apply early pressure with efficient creatures like Chittering Rats and Gray Merchant of Asphodel, while disrupting the opponent's game plan with removal spells like Tendrils of Corruption and Geth's Verdict. The deck aims to control the board with cards like Pestilence and Cuombajj Witches, while also gaining card advantage with Phyrexian Rager and Sign in Blood. The deck utilizes graveyard recursion with Unearth and aims to outvalue the opponent with powerful threats like Gurmag Angler."
        },
        {
            "date": "2015-11-23",
            "player": "MrBroom",
            "result": 3,
            "anchor_uri": "https://mtgtop8.com/event?e=10982&d=262535&f=PAU",
            "mainboard": [
                {
                    "count": 4,
                    "name": "Fangren Marauder"
                },
                {
                    "count": 1,
                    "name": "Maul Splicer"
                },
                {
                    "count": 4,
                    "name": "Mulldrifter"
                },
                {
                    "count": 4,
                    "name": "Sea Gate Oracle"
                },
                {
                    "count": 4,
                    "name": "Ancient Stirrings"
                },
                {
                    "count": 2,
                    "name": "Firebolt"
                },
                {
                    "count": 2,
                    "name": "Flame Slash"
                },
                {
                    "count": 2,
                    "name": "Rolling Thunder"
                },
                {
                    "count": 4,
                    "name": "Chromatic Sphere"
                },
                {
                    "count": 4,
                    "name": "Chromatic Star"
                },
                {
                    "count": 1,
                    "name": "Elsewhere Flask"
                },
                {
                    "count": 4,
                    "name": "Expedition Map"
                },
                {
                    "count": 4,
                    "name": "Prophetic Prism"
                },
                {
                    "count": 4,
                    "name": "Haunted Fengraf"
                },
                {
                    "count": 3,
                    "name": "Shimmering Grotto"
                },
                {
                    "count": 1,
                    "name": "Smoldering Crater"
                },
                {
                    "count": 4,
                    "name": "Urza's Mine"
                },
                {
                    "count": 4,
                    "name": "Urza's Power Plant"
                },
                {
                    "count": 4,
                    "name": "Urza's Tower"
                }
            ],
            "sideboard": [
                {
                    "count": 1,
                    "name": "Firebolt"
                },
                {
                    "count": 1,
                    "name": "Flame Slash"
                },
                {
                    "count": 2,
                    "name": "Ancient Grudge"
                },
                {
                    "count": 2,
                    "name": "Chainer's Edict"
                },
                {
                    "count": 3,
                    "name": "Circle of Protection: Red"
                },
                {
                    "count": 2,
                    "name": "Earth Rift"
                },
                {
                    "count": 2,
                    "name": "Evincar's Justice"
                },
                {
                    "count": 2,
                    "name": "Ray of Revelation"
                }
            ],
            "notes": "The main focus of this deck is to quickly assemble the Urzatron - Urza's Mine, Power Plant, and Tower - to generate a large amount of mana. This mana is then used to cast powerful spells like Rolling Thunder to control the board and overwhelm opponents. The deck also includes various card draw and filtering effects to ensure consistency in drawing into key pieces and threats. The goal is to outvalue and outlast opponents through efficient mana production and card advantage."
        },
        {
            "date": "2015-11-23",
            "player": "Alicorn",
            "result": 4,
            "anchor_uri": "https://mtgtop8.com/event?e=10982&d=262534&f=PAU",
            "mainboard": [
                {
                    "count": 4,
                    "name": "Cloud of Faeries"
                },
                {
                    "count": 4,
                    "name": "Delver of Secrets"
                },
                {
                    "count": 4,
                    "name": "Ninja of the Deep Hours"
                },
                {
                    "count": 4,
                    "name": "Spellstutter Sprite"
                },
                {
                    "count": 4,
                    "name": "Spire Golem"
                },
                {
                    "count": 4,
                    "name": "Ponder"
                },
                {
                    "count": 4,
                    "name": "Preordain"
                },
                {
                    "count": 4,
                    "name": "Counterspell"
                },
                {
                    "count": 2,
                    "name": "Deprive"
                },
                {
                    "count": 2,
                    "name": "Gush"
                },
                {
                    "count": 3,
                    "name": "Mana Leak"
                },
                {
                    "count": 3,
                    "name": "Snap"
                },
                {
                    "count": 1,
                    "name": "Bonesplitter"
                },
                {
                    "count": 17,
                    "name": "Island"
                }
            ],
            "sideboard": [
                {
                    "count": 2,
                    "name": "Annul"
                },
                {
                    "count": 3,
                    "name": "Curse of Chains"
                },
                {
                    "count": 2,
                    "name": "Dispel"
                },
                {
                    "count": 3,
                    "name": "Hydroblast"
                },
                {
                    "count": 2,
                    "name": "One-Eyed Scarecrow"
                },
                {
                    "count": 3,
                    "name": "Stormbound Geist"
                }
            ],
            "notes": "This deck focuses on quickly dropping creatures with evasion like Ninja of the Deep Hours and Delver of Secrets to apply early pressure on the opponent. Utilizing cheap interaction like Spellstutter Sprite and Counterspell to disrupt the opponent's game plan, while maintaining card advantage with cards like Ponder and Preordain. The deck leans towards a tempo playstyle, using cards like Cloud of Faeries and Gush to generate extra mana and keep applying pressure. With a focus on efficient creatures and countermagic, this deck aims to control the board while dealing damage consistently."
        }
    ],
    "rounds": [],
    "standings": []
}